<?xml version="1.0" encoding="UTF-8"?>
<EXPORTMAIL>
  <STRLOAIVANBAN>Công văn</STRLOAIVANBAN>
  <STRKYHIEU>443/CV/STC-THTK</STRKYHIEU>
  <STRTRICHYEU>Công văn về việc đóng mã số dự án đầu tư XDCB hoàn thành trên địa bàn huyện Ứng Hòa</STRTRICHYEU>
  <STRNGAYKY>22/01/2021</STRNGAYKY>
  <STRNGUOIKY>Kiều Xuân Nghị</STRNGUOIKY>
  <STRCHUCDANH>Phó giám đốc</STRCHUCDANH>
  <STRNOIGUI>Sở Tài chính</STRNOIGUI>
  <STRNGAYHOP></STRNGAYHOP>
  <STRDIADIEM></STRDIADIEM>
  <STRTHOIGIANHOP></STRTHOIGIANHOP>
</EXPORTMAIL>
